[
  {
    "type": 1,
    "word": "aaa"
  },
  {
    "type": 1,
    "word": "abrahami"
  },
  {
    "type": 1,
    "word": "abramovich"
  },
  {
    "type": 1,
    "word": "account"
  },
  {
    "type": 1,
    "word": "acrotomoph"
  },
  {
    "type": 1,
    "word": "activision"
  },
  {
    "type": 1,
    "word": "adidas"
  },
  {
    "type": 1,
    "word": "admin"
  },
  {
    "type": 1,
    "word": "administrator"
  },
  {
    "type": 1,
    "word": "adobe"
  },
  {
    "type": 1,
    "word": "adoifhilter"
  },
  {
    "type": 1,
    "word": "adolf"
  },
  {
    "type": 1,
    "word": "adolffhilter"
  },
  {
    "type": 1,
    "word": "adolfh"
  },
  {
    "type": 1,
    "word": "adolfhitler"
  },
  {
    "type": 1,
    "word": "adolphe"
  },
  {
    "type": 1,
    "word": "affenarsch"
  },
  {
    "type": 1,
    "word": "affensack"
  },
  {
    "type": 1,
    "word": "affentitte"
  },
  {
    "type": 1,
    "word": "afganis"
  },
  {
    "type": 1,
    "word": "afghan"
  },
  {
    "type": 1,
    "word": "Afghanistan"
  },
  {
    "type": 1,
    "word": "Africa"
  },
  {
    "type": 1,
    "word": "Afrika"
  },
  {
    "type": 1,
    "word": "Albania"
  },
  {
    "type": 1,
    "word": "Algeria"
  },
  {
    "type": 1,
    "word": "america"
  },
  {
    "type": 1,
    "word": "Andorra"
  },
  {
    "type": 1,
    "word": "Angola"
  },
  {
    "type": 1,
    "word": "Anguilla"
  },
  {
    "type": 1,
    "word": "aniling"
  },
  {
    "type": 1,
    "word": "ankara"
  },
  {
    "type": 1,
    "word": "Anonyme"
  },
  {
    "type": 1,
    "word": "Anonymo"
  },
  {
    "type": 1,
    "word": "Antarctica"
  },
  {
    "type": 1,
    "word": "Antigua"
  },
  {
    "type": 1,
    "word": "apeshit"
  },
  {
    "type": 1,
    "word": "Arabemir"
  },
  {
    "type": 1,
    "word": "Argentina"
  },
  {
    "type": 1,
    "word": "Armenia"
  },
  {
    "type": 1,
    "word": "Arschficker"
  },
  {
    "type": 1,
    "word": "Arschgeige"
  },
  {
    "type": 1,
    "word": "Arschgesicht"
  },
  {
    "type": 1,
    "word": "Arschloch"
  },
  {
    "type": 1,
    "word": "arsehol"
  },
  {
    "type": 1,
    "word": "assbag"
  },
  {
    "type": 1,
    "word": "assbite"
  },
  {
    "type": 1,
    "word": "assclown"
  },
  {
    "type": 1,
    "word": "asscock"
  },
  {
    "type": 1,
    "word": "asscrack"
  },
  {
    "type": 1,
    "word": "assface"
  },
  {
    "type": 1,
    "word": "assgoblin"
  },
  {
    "type": 1,
    "word": "asshat"
  },
  {
    "type": 1,
    "word": "asshead"
  },
  {
    "type": 1,
    "word": "asshole"
  },
  {
    "type": 1,
    "word": "assjacker"
  },
  {
    "type": 1,
    "word": "asslick"
  },
  {
    "type": 1,
    "word": "assmonk"
  },
  {
    "type": 1,
    "word": "assmunch"
  },
  {
    "type": 1,
    "word": "asspirat"
  },
  {
    "type": 1,
    "word": "assrap"
  },
  {
    "type": 1,
    "word": "asswad"
  },
  {
    "type": 1,
    "word": "asswipe"
  },
  {
    "type": 1,
    "word": "atheist"
  },
  {
    "type": 1,
    "word": "athens"
  },
  {
    "type": 1,
    "word": "atlanta"
  },
  {
    "type": 1,
    "word": "atomicbomb"
  },
  {
    "type": 1,
    "word": "auckland"
  },
  {
    "type": 1,
    "word": "Australia"
  },
  {
    "type": 1,
    "word": "Austria"
  },
  {
    "type": 1,
    "word": "Azerbaijan"
  },
  {
    "type": 1,
    "word": "babaca"
  },
  {
    "type": 1,
    "word": "bacharel"
  },
  {
    "type": 1,
    "word": "baghdad"
  },
  {
    "type": 1,
    "word": "Bahamas"
  },
  {
    "type": 1,
    "word": "Bahrain"
  },
  {
    "type": 1,
    "word": "ballsack"
  },
  {
    "type": 1,
    "word": "baltimore"
  },
  {
    "type": 1,
    "word": "bangalore"
  },
  {
    "type": 1,
    "word": "bangbros"
  },
  {
    "type": 1,
    "word": "bangkok"
  },
  {
    "type": 1,
    "word": "Bangladesh"
  },
  {
    "type": 1,
    "word": "barack"
  },
  {
    "type": 1,
    "word": "Barbados"
  },
  {
    "type": 1,
    "word": "Barbuda"
  },
  {
    "type": 1,
    "word": "barcelon"
  },
  {
    "type": 1,
    "word": "bareback"
  },
  {
    "type": 1,
    "word": "bastard"
  },
  {
    "type": 1,
    "word": "bastardo"
  },
  {
    "type": 1,
    "word": "bastinado"
  },
  {
    "type": 1,
    "word": "batgirl"
  },
  {
    "type": 1,
    "word": "batman"
  },
  {
    "type": 1,
    "word": "bbb"
  },
  {
    "type": 1,
    "word": "bbc"
  },
  {
    "type": 1,
    "word": "bdsm"
  },
  {
    "type": 1,
    "word": "beethoven"
  },
  {
    "type": 1,
    "word": "beijing"
  },
  {
    "type": 1,
    "word": "Belarus"
  },
  {
    "type": 1,
    "word": "Belgium"
  },
  {
    "type": 1,
    "word": "Belize"
  },
  {
    "type": 1,
    "word": "berlin"
  },
  {
    "type": 1,
    "word": "Bermuda"
  },
  {
    "type": 1,
    "word": "bethesda"
  },
  {
    "type": 1,
    "word": "beyonce"
  },
  {
    "type": 1,
    "word": "Bhutan"
  },
  {
    "type": 1,
    "word": "billgates"
  },
  {
    "type": 1,
    "word": "bioware"
  },
  {
    "type": 1,
    "word": "birmingham"
  },
  {
    "type": 1,
    "word": "bitch"
  },
  {
    "type": 1,
    "word": "bleach"
  },
  {
    "type": 1,
    "word": "blowjob"
  },
  {
    "type": 1,
    "word": "blowjob"
  },
  {
    "type": 1,
    "word": "blumpkin"
  },
  {
    "type": 1,
    "word": "bmw"
  },
  {
    "type": 1,
    "word": "boahancock"
  },
  {
    "type": 1,
    "word": "bogota"
  },
  {
    "type": 1,
    "word": "Bolivia"
  },
  {
    "type": 1,
    "word": "bollock"
  },
  {
    "type": 1,
    "word": "bollok"
  },
  {
    "type": 1,
    "word": "bollox"
  },
  {
    "type": 1,
    "word": "bollywood"
  },
  {
    "type": 1,
    "word": "boob"
  },
  {
    "type": 1,
    "word": "Bosnia"
  },
  {
    "type": 1,
    "word": "boston"
  },
  {
    "type": 1,
    "word": "Botswana"
  },
  {
    "type": 1,
    "word": "bradpit"
  },
  {
    "type": 1,
    "word": "Brazil"
  },
  {
    "type": 1,
    "word": "brisbane"
  },
  {
    "type": 1,
    "word": "bshit"
  },
  {
    "type": 1,
    "word": "budapest"
  },
  {
    "type": 1,
    "word": "buddh"
  },
  {
    "type": 1,
    "word": "buenosair"
  },
  {
    "type": 1,
    "word": "bugger"
  },
  {
    "type": 1,
    "word": "bukkake"
  },
  {
    "type": 1,
    "word": "Bulgaria"
  },
  {
    "type": 1,
    "word": "bulldyke"
  },
  {
    "type": 1,
    "word": "bullshit"
  },
  {
    "type": 1,
    "word": "bundesliga"
  },
  {
    "type": 1,
    "word": "bunghole"
  },
  {
    "type": 1,
    "word": "burgerking"
  },
  {
    "type": 1,
    "word": "Burkina"
  },
  {
    "type": 1,
    "word": "Burundi"
  },
  {
    "type": 1,
    "word": "buttcheeks"
  },
  {
    "type": 1,
    "word": "butthole"
  },
  {
    "type": 1,
    "word": "buzzfeed"
  },
  {
    "type": 1,
    "word": "Caledonia"
  },
  {
    "type": 1,
    "word": "calientapollas"
  },
  {
    "type": 1,
    "word": "Cambodia"
  },
  {
    "type": 1,
    "word": "cameltoe"
  },
  {
    "type": 1,
    "word": "Cameroon"
  },
  {
    "type": 1,
    "word": "camgirl"
  },
  {
    "type": 1,
    "word": "campinas"
  },
  {
    "type": 1,
    "word": "camslut"
  },
  {
    "type": 1,
    "word": "Canada"
  },
  {
    "type": 1,
    "word": "candycrush"
  },
  {
    "type": 1,
    "word": "caodaism"
  },
  {
    "type": 1,
    "word": "capcom"
  },
  {
    "type": 1,
    "word": "Capeverde"
  },
  {
    "type": 1,
    "word": "caralho"
  },
  {
    "type": 1,
    "word": "carllewis"
  },
  {
    "type": 1,
    "word": "carpetmuncher"
  },
  {
    "type": 1,
    "word": "catholic"
  },
  {
    "type": 1,
    "word": "catholik"
  },
  {
    "type": 1,
    "word": "catholiq"
  },
  {
    "type": 1,
    "word": "ccc"
  },
  {
    "type": 1,
    "word": "cheondois"
  },
  {
    "type": 1,
    "word": "chesticle"
  },
  {
    "type": 1,
    "word": "chicago"
  },
  {
    "type": 1,
    "word": "China"
  },
  {
    "type": 1,
    "word": "chipotle"
  },
  {
    "type": 1,
    "word": "christian"
  },
  {
    "type": 1,
    "word": "Chupame"
  },
  {
    "type": 1,
    "word": "chuparola"
  },
  {
    "type": 1,
    "word": "churchill"
  },
  {
    "type": 1,
    "word": "cincinnati"
  },
  {
    "type": 1,
    "word": "circlejerk"
  },
  {
    "type": 1,
    "word": "clashofclan"
  },
  {
    "type": 1,
    "word": "cleveland"
  },
  {
    "type": 1,
    "word": "clinton"
  },
  {
    "type": 1,
    "word": "clitface"
  },
  {
    "type": 1,
    "word": "clitoris"
  },
  {
    "type": 1,
    "word": "cocacola"
  },
  {
    "type": 1,
    "word": "cocain"
  },
  {
    "type": 1,
    "word": "cockass"
  },
  {
    "type": 1,
    "word": "cockbite"
  },
  {
    "type": 1,
    "word": "cockburg"
  },
  {
    "type": 1,
    "word": "cockface"
  },
  {
    "type": 1,
    "word": "cockhead"
  },
  {
    "type": 1,
    "word": "cockj"
  },
  {
    "type": 1,
    "word": "cockk"
  },
  {
    "type": 1,
    "word": "cockm"
  },
  {
    "type": 1,
    "word": "cockno"
  },
  {
    "type": 1,
    "word": "cocknu"
  },
  {
    "type": 1,
    "word": "cocksm"
  },
  {
    "type": 1,
    "word": "cocksn"
  },
  {
    "type": 1,
    "word": "cocksuc"
  },
  {
    "type": 1,
    "word": "cockwa"
  },
  {
    "type": 1,
    "word": "cocochanel"
  },
  {
    "type": 1,
    "word": "Cojonazos"
  },
  {
    "type": 1,
    "word": "Colombia"
  },
  {
    "type": 1,
    "word": "colombus"
  },
  {
    "type": 1,
    "word": "communist"
  },
  {
    "type": 1,
    "word": "Comoros"
  },
  {
    "type": 1,
    "word": "conasse"
  },
  {
    "type": 1,
    "word": "condom"
  },
  {
    "type": 1,
    "word": "connard"
  },
  {
    "type": 1,
    "word": "connard"
  },
  {
    "type": 1,
    "word": "CookIslands"
  },
  {
    "type": 1,
    "word": "copenhagen"
  },
  {
    "type": 1,
    "word": "coprolagnia"
  },
  {
    "type": 1,
    "word": "coproph"
  },
  {
    "type": 1,
    "word": "cornhole"
  },
  {
    "type": 1,
    "word": "CostaRica"
  },
  {
    "type": 1,
    "word": "Cote DIvoire"
  },
  {
    "type": 1,
    "word": "couilles"
  },
  {
    "type": 1,
    "word": "cowgirl"
  },
  {
    "type": 1,
    "word": "creampie"
  },
  {
    "type": 1,
    "word": "Croatia"
  },
  {
    "type": 1,
    "word": "cumbub"
  },
  {
    "type": 1,
    "word": "cumdump"
  },
  {
    "type": 1,
    "word": "cumguz"
  },
  {
    "type": 1,
    "word": "cumjoc"
  },
  {
    "type": 1,
    "word": "cumming"
  },
  {
    "type": 1,
    "word": "cumonmyface"
  },
  {
    "type": 1,
    "word": "cumslut"
  },
  {
    "type": 1,
    "word": "cumtart"
  },
  {
    "type": 1,
    "word": "cunnie"
  },
  {
    "type": 1,
    "word": "cunnilin"
  },
  {
    "type": 1,
    "word": "Curacao"
  },
  {
    "type": 1,
    "word": "Cyprus"
  },
  {
    "type": 1,
    "word": "Czechre"
  },
  {
    "type": 1,
    "word": "daech"
  },
  {
    "type": 1,
    "word": "dailymotion"
  },
  {
    "type": 1,
    "word": "dalailama"
  },
  {
    "type": 1,
    "word": "dallas"
  },
  {
    "type": 1,
    "word": "darthvader"
  },
  {
    "type": 1,
    "word": "Darussalam"
  },
  {
    "type": 1,
    "word": "daterape"
  },
  {
    "type": 1,
    "word": "davidbeckham"
  },
  {
    "type": 1,
    "word": "davinci"
  },
  {
    "type": 1,
    "word": "ddd"
  },
  {
    "type": 1,
    "word": "deepthroat"
  },
  {
    "type": 1,
    "word": "deggo"
  },
  {
    "type": 1,
    "word": "dejaneiro"
  },
  {
    "type": 1,
    "word": "delhi"
  },
  {
    "type": 1,
    "word": "democrat"
  },
  {
    "type": 1,
    "word": "dendroph"
  },
  {
    "type": 1,
    "word": "Denmark"
  },
  {
    "type": 1,
    "word": "Desgraciado"
  },
  {
    "type": 1,
    "word": "desmondtutu"
  },
  {
    "type": 1,
    "word": "dipshit"
  },
  {
    "type": 1,
    "word": "disney"
  },
  {
    "type": 1,
    "word": "Djibouti"
  },
  {
    "type": 1,
    "word": "djihad"
  },
  {
    "type": 1,
    "word": "dluffy"
  },
  {
    "type": 1,
    "word": "doggiesty"
  },
  {
    "type": 1,
    "word": "doggysty"
  },
  {
    "type": 1,
    "word": "dolcett"
  },
  {
    "type": 1,
    "word": "Dominican"
  },
  {
    "type": 1,
    "word": "donaldtrump"
  },
  {
    "type": 1,
    "word": "dookie"
  },
  {
    "type": 1,
    "word": "doucheb"
  },
  {
    "type": 1,
    "word": "douchef"
  },
  {
    "type": 1,
    "word": "douchew"
  },
  {
    "type": 1,
    "word": "Drecksau"
  },
  {
    "type": 1,
    "word": "drogendealer"
  },
  {
    "type": 1,
    "word": "drugdealer"
  },
  {
    "type": 1,
    "word": "drugsdealer"
  },
  {
    "type": 1,
    "word": "dteach"
  },
  {
    "type": 1,
    "word": "dukenukem"
  },
  {
    "type": 1,
    "word": "dumass"
  },
  {
    "type": 1,
    "word": "dumbass"
  },
  {
    "type": 1,
    "word": "dumbsh"
  },
  {
    "type": 1,
    "word": "dusseldorf"
  },
  {
    "type": 1,
    "word": "eagame"
  },
  {
    "type": 1,
    "word": "Ecuador"
  },
  {
    "type": 1,
    "word": "eee"
  },
  {
    "type": 1,
    "word": "Egypt"
  },
  {
    "type": 1,
    "word": "einstein"
  },
  {
    "type": 1,
    "word": "ejacul"
  },
  {
    "type": 1,
    "word": "ejakul"
  },
  {
    "type": 1,
    "word": "elassad"
  },
  {
    "type": 1,
    "word": "electronicarts"
  },
  {
    "type": 1,
    "word": "ElSalvador"
  },
  {
    "type": 1,
    "word": "elvispresley"
  },
  {
    "type": 1,
    "word": "Emirates"
  },
  {
    "type": 1,
    "word": "enculer"
  },
  {
    "type": 1,
    "word": "England"
  },
  {
    "type": 1,
    "word": "entermat"
  },
  {
    "type": 1,
    "word": "entertainment"
  },
  {
    "type": 1,
    "word": "Eritrea"
  },
  {
    "type": 1,
    "word": "escroto"
  },
  {
    "type": 1,
    "word": "Estonia"
  },
  {
    "type": 1,
    "word": "Ethiopia"
  },
  {
    "type": 1,
    "word": "eunuch"
  },
  {
    "type": 1,
    "word": "europe"
  },
  {
    "type": 1,
    "word": "facebook"
  },
  {
    "type": 1,
    "word": "fagbag"
  },
  {
    "type": 1,
    "word": "faggit"
  },
  {
    "type": 1,
    "word": "faggot"
  },
  {
    "type": 1,
    "word": "faghag"
  },
  {
    "type": 1,
    "word": "fagtard"
  },
  {
    "type": 1,
    "word": "Falkland"
  },
  {
    "type": 1,
    "word": "falongong"
  },
  {
    "type": 1,
    "word": "falundafa"
  },
  {
    "type": 1,
    "word": "falungong"
  },
  {
    "type": 1,
    "word": "fannyflap"
  },
  {
    "type": 1,
    "word": "faschist"
  },
  {
    "type": 1,
    "word": "fascho"
  },
  {
    "type": 1,
    "word": "fascist"
  },
  {
    "type": 1,
    "word": "fatass"
  },
  {
    "type": 1,
    "word": "federer"
  },
  {
    "type": 1,
    "word": "fellatio"
  },
  {
    "type": 1,
    "word": "feltch"
  },
  {
    "type": 1,
    "word": "femdom"
  },
  {
    "type": 1,
    "word": "ferrari"
  },
  {
    "type": 1,
    "word": "fff"
  },
  {
    "type": 1,
    "word": "fidelcastro"
  },
  {
    "type": 1,
    "word": "fifa"
  },
  {
    "type": 1,
    "word": "figging"
  },
  {
    "type": 1,
    "word": "filsdepute"
  },
  {
    "type": 1,
    "word": "filsdepute"
  },
  {
    "type": 1,
    "word": "fingerbang"
  },
  {
    "type": 1,
    "word": "fingering"
  },
  {
    "type": 1,
    "word": "Finland"
  },
  {
    "type": 1,
    "word": "fisting"
  },
  {
    "type": 1,
    "word": "fliff"
  },
  {
    "type": 1,
    "word": "fliif"
  },
  {
    "type": 1,
    "word": "flyf"
  },
  {
    "type": 1,
    "word": "flyff"
  },
  {
    "type": 1,
    "word": "footjob"
  },
  {
    "type": 1,
    "word": "forumadmin"
  },
  {
    "type": 1,
    "word": "France"
  },
  {
    "type": 1,
    "word": "frankfurt"
  },
  {
    "type": 1,
    "word": "freestuff"
  },
  {
    "type": 1,
    "word": "freetoplay"
  },
  {
    "type": 1,
    "word": "french"
  },
  {
    "type": 1,
    "word": "frotting"
  },
  {
    "type": 1,
    "word": "fuck"
  },
  {
    "type": 1,
    "word": "fudgepacker"
  },
  {
    "type": 1,
    "word": "fukuoka"
  },
  {
    "type": 1,
    "word": "fuuck"
  },
  {
    "type": 1,
    "word": "fuvck"
  },
  {
    "type": 1,
    "word": "fvck"
  },
  {
    "type": 1,
    "word": "fvvck"
  },
  {
    "type": 1,
    "word": "Gaememaster"
  },
  {
    "type": 1,
    "word": "gala"
  },
  {
    "type": 1,
    "word": "Gamaemaster"
  },
  {
    "type": 1,
    "word": "Gambia"
  },
  {
    "type": 1,
    "word": "game"
  },
  {
    "type": 1,
    "word": "Gameamaster"
  },
  {
    "type": 1,
    "word": "gameloft"
  },
  {
    "type": 1,
    "word": "Gamemaester"
  },
  {
    "type": 1,
    "word": "Gamemastaer"
  },
  {
    "type": 1,
    "word": "Gamemastear"
  },
  {
    "type": 1,
    "word": "gamemaster"
  },
  {
    "type": 1,
    "word": "GameMaster"
  },
  {
    "type": 1,
    "word": "Gamemeaster"
  },
  {
    "type": 1,
    "word": "gameofthrones"
  },
  {
    "type": 1,
    "word": "gandalf"
  },
  {
    "type": 1,
    "word": "gandalff"
  },
  {
    "type": 1,
    "word": "ganddalf"
  },
  {
    "type": 1,
    "word": "gandhi"
  },
  {
    "type": 1,
    "word": "gangbang"
  },
  {
    "type": 1,
    "word": "gangbang"
  },
  {
    "type": 1,
    "word": "gangsta"
  },
  {
    "type": 1,
    "word": "gangster"
  },
  {
    "type": 1,
    "word": "gayass"
  },
  {
    "type": 1,
    "word": "gaybob"
  },
  {
    "type": 1,
    "word": "gaydo"
  },
  {
    "type": 1,
    "word": "gaylord"
  },
  {
    "type": 1,
    "word": "gaytard"
  },
  {
    "type": 1,
    "word": "gaywad"
  },
  {
    "type": 1,
    "word": "Geamemaster"
  },
  {
    "type": 1,
    "word": "genital"
  },
  {
    "type": 1,
    "word": "genitals"
  },
  {
    "type": 1,
    "word": "genocid"
  },
  {
    "type": 1,
    "word": "georgebush"
  },
  {
    "type": 1,
    "word": "georgewbush"
  },
  {
    "type": 1,
    "word": "georgia"
  },
  {
    "type": 1,
    "word": "Germany"
  },
  {
    "type": 1,
    "word": "ggg"
  },
  {
    "type": 1,
    "word": "Gibraltar"
  },
  {
    "type": 1,
    "word": "Gilipollas"
  },
  {
    "type": 1,
    "word": "givehead"
  },
  {
    "type": 1,
    "word": "givhead"
  },
  {
    "type": 1,
    "word": "givinghead"
  },
  {
    "type": 1,
    "word": "gmaccount"
  },
  {
    "type": 1,
    "word": "gmfaker"
  },
  {
    "type": 1,
    "word": "gmmember"
  },
  {
    "type": 1,
    "word": "gmteam"
  },
  {
    "type": 1,
    "word": "goatcx"
  },
  {
    "type": 1,
    "word": "goatse"
  },
  {
    "type": 1,
    "word": "gohan"
  },
  {
    "type": 1,
    "word": "gokkun"
  },
  {
    "type": 1,
    "word": "goku"
  },
  {
    "type": 1,
    "word": "goldseller"
  },
  {
    "type": 1,
    "word": "gollum"
  },
  {
    "type": 1,
    "word": "golum"
  },
  {
    "type": 1,
    "word": "goluum"
  },
  {
    "type": 1,
    "word": "goodpoop"
  },
  {
    "type": 1,
    "word": "google"
  },
  {
    "type": 1,
    "word": "gorbachev"
  },
  {
    "type": 1,
    "word": "goregasm"
  },
  {
    "type": 1,
    "word": "gpatato"
  },
  {
    "type": 1,
    "word": "gpotato"
  },
  {
    "type": 1,
    "word": "gpotatto"
  },
  {
    "type": 1,
    "word": "gratuit"
  },
  {
    "type": 1,
    "word": "Greece"
  },
  {
    "type": 1,
    "word": "Greenland"
  },
  {
    "type": 1,
    "word": "guadalajara"
  },
  {
    "type": 1,
    "word": "Guadeloupe"
  },
  {
    "type": 1,
    "word": "Guatemala"
  },
  {
    "type": 1,
    "word": "gucci"
  },
  {
    "type": 1,
    "word": "Guernsey"
  },
  {
    "type": 1,
    "word": "Guinea"
  },
  {
    "type": 1,
    "word": "GuineaBissau"
  },
  {
    "type": 1,
    "word": "gungho"
  },
  {
    "type": 1,
    "word": "Guyana"
  },
  {
    "type": 1,
    "word": "Haiti"
  },
  {
    "type": 1,
    "word": "handjob"
  },
  {
    "type": 1,
    "word": "hansolo"
  },
  {
    "type": 1,
    "word": "hayday"
  },
  {
    "type": 1,
    "word": "heroin"
  },
  {
    "type": 1,
    "word": "Herzegovina"
  },
  {
    "type": 1,
    "word": "hewlettpackard"
  },
  {
    "type": 1,
    "word": "hhh"
  },
  {
    "type": 1,
    "word": "hiitler"
  },
  {
    "type": 1,
    "word": "himmler"
  },
  {
    "type": 1,
    "word": "hindui"
  },
  {
    "type": 1,
    "word": "hinrichtung"
  },
  {
    "type": 1,
    "word": "hitler"
  },
  {
    "type": 1,
    "word": "hitller"
  },
  {
    "type": 1,
    "word": "hittler"
  },
  {
    "type": 1,
    "word": "hoahaoi"
  },
  {
    "type": 1,
    "word": "hobbit"
  },
  {
    "type": 1,
    "word": "hochiminh"
  },
  {
    "type": 1,
    "word": "hollywood"
  },
  {
    "type": 1,
    "word": "holocaust"
  },
  {
    "type": 1,
    "word": "holokaust"
  },
  {
    "type": 1,
    "word": "homosex"
  },
  {
    "type": 1,
    "word": "Honduras"
  },
  {
    "type": 1,
    "word": "HongKong"
  },
  {
    "type": 1,
    "word": "honkey"
  },
  {
    "type": 1,
    "word": "hooker"
  },
  {
    "type": 1,
    "word": "hooker"
  },
  {
    "type": 1,
    "word": "hulk"
  },
  {
    "type": 1,
    "word": "humping"
  },
  {
    "type": 1,
    "word": "Hungary"
  },
  {
    "type": 1,
    "word": "Hurensohn "
  },
  {
    "type": 1,
    "word": "hussein"
  },
  {
    "type": 1,
    "word": "hyderabad"
  },
  {
    "type": 1,
    "word": "Iceland"
  },
  {
    "type": 1,
    "word": "ichfickedich"
  },
  {
    "type": 1,
    "word": "ichhassedich"
  },
  {
    "type": 1,
    "word": "ichwillficken"
  },
  {
    "type": 1,
    "word": "iheartradio"
  },
  {
    "type": 1,
    "word": "iii"
  },
  {
    "type": 1,
    "word": "ikillu"
  },
  {
    "type": 1,
    "word": "ikillyou"
  },
  {
    "type": 1,
    "word": "ilovedick"
  },
  {
    "type": 1,
    "word": "ilovepussy"
  },
  {
    "type": 1,
    "word": "ilovewow"
  },
  {
    "type": 1,
    "word": "India"
  },
  {
    "type": 1,
    "word": "Indonesia"
  },
  {
    "type": 1,
    "word": "instagram"
  },
  {
    "type": 1,
    "word": "Ireland"
  },
  {
    "type": 1,
    "word": "Islam"
  },
  {
    "type": 1,
    "word": "Isleofman"
  },
  {
    "type": 1,
    "word": "Israel"
  },
  {
    "type": 1,
    "word": "istanbul"
  },
  {
    "type": 1,
    "word": "Italia"
  },
  {
    "type": 1,
    "word": "Italy"
  },
  {
    "type": 1,
    "word": "itemsell"
  },
  {
    "type": 1,
    "word": "jackass"
  },
  {
    "type": 1,
    "word": "jagoff"
  },
  {
    "type": 1,
    "word": "jakarta"
  },
  {
    "type": 1,
    "word": "Jamaica"
  },
  {
    "type": 1,
    "word": "Japan"
  },
  {
    "type": 1,
    "word": "jeddah"
  },
  {
    "type": 1,
    "word": "jefferson"
  },
  {
    "type": 1,
    "word": "jerkass"
  },
  {
    "type": 1,
    "word": "jerkof"
  },
  {
    "type": 1,
    "word": "jerkoff"
  },
  {
    "type": 1,
    "word": "jerusalem"
  },
  {
    "type": 1,
    "word": "jesus"
  },
  {
    "type": 1,
    "word": "jfk"
  },
  {
    "type": 1,
    "word": "jigaboo"
  },
  {
    "type": 1,
    "word": "jiggaboo"
  },
  {
    "type": 1,
    "word": "jiggerboo"
  },
  {
    "type": 1,
    "word": "jihad"
  },
  {
    "type": 1,
    "word": "jizz"
  },
  {
    "type": 1,
    "word": "jjj"
  },
  {
    "type": 1,
    "word": "jkrowling"
  },
  {
    "type": 1,
    "word": "johannesburg"
  },
  {
    "type": 1,
    "word": "johnpaul"
  },
  {
    "type": 1,
    "word": "Jordania"
  },
  {
    "type": 1,
    "word": "judais"
  },
  {
    "type": 1,
    "word": "kabam"
  },
  {
    "type": 1,
    "word": "karachi"
  },
  {
    "type": 1,
    "word": "kardashian"
  },
  {
    "type": 1,
    "word": "katowice"
  },
  {
    "type": 1,
    "word": "Kazakhstan"
  },
  {
    "type": 1,
    "word": "kenobi"
  },
  {
    "type": 1,
    "word": "Kenya"
  },
  {
    "type": 1,
    "word": "khartoum"
  },
  {
    "type": 1,
    "word": "kinkster"
  },
  {
    "type": 1,
    "word": "kkk"
  },
  {
    "type": 1,
    "word": "kkluxk"
  },
  {
    "type": 1,
    "word": "klucluxklan"
  },
  {
    "type": 1,
    "word": "kluxcluxclan"
  },
  {
    "type": 1,
    "word": "kluxkluxklan "
  },
  {
    "type": 1,
    "word": "knobbing"
  },
  {
    "type": 1,
    "word": "kolkata"
  },
  {
    "type": 1,
    "word": "kommunist"
  },
  {
    "type": 1,
    "word": "konami"
  },
  {
    "type": 1,
    "word": "kooch"
  },
  {
    "type": 1,
    "word": "Korea"
  },
  {
    "type": 1,
    "word": "kostenfrei"
  },
  {
    "type": 1,
    "word": "kostenlos"
  },
  {
    "type": 1,
    "word": "krillin"
  },
  {
    "type": 1,
    "word": "kualalump"
  },
  {
    "type": 1,
    "word": "kuklux"
  },
  {
    "type": 1,
    "word": "kukluxklan"
  },
  {
    "type": 1,
    "word": "Kuwait"
  },
  {
    "type": 1,
    "word": "kyoto"
  },
  {
    "type": 1,
    "word": "Kyrgyzstan"
  },
  {
    "type": 1,
    "word": "ladygaga"
  },
  {
    "type": 1,
    "word": "lameass"
  },
  {
    "type": 1,
    "word": "lardass"
  },
  {
    "type": 1,
    "word": "larrypage"
  },
  {
    "type": 1,
    "word": "Latvia"
  },
  {
    "type": 1,
    "word": "Lebanon"
  },
  {
    "type": 1,
    "word": "lesbo"
  },
  {
    "type": 1,
    "word": "Lesotho"
  },
  {
    "type": 1,
    "word": "lezzie"
  },
  {
    "type": 1,
    "word": "Liberia"
  },
  {
    "type": 1,
    "word": "Libya"
  },
  {
    "type": 1,
    "word": "Liechtenstein"
  },
  {
    "type": 1,
    "word": "lineage"
  },
  {
    "type": 1,
    "word": "lineagetwo"
  },
  {
    "type": 1,
    "word": "linkedin"
  },
  {
    "type": 1,
    "word": "lionelmessi"
  },
  {
    "type": 1,
    "word": "Lithuania"
  },
  {
    "type": 1,
    "word": "lll"
  },
  {
    "type": 1,
    "word": "london"
  },
  {
    "type": 1,
    "word": "losangeles"
  },
  {
    "type": 1,
    "word": "louispasteur"
  },
  {
    "type": 1,
    "word": "louisvuitton"
  },
  {
    "type": 1,
    "word": "lucasart"
  },
  {
    "type": 1,
    "word": "lucifer"
  },
  {
    "type": 1,
    "word": "luckystrike"
  },
  {
    "type": 1,
    "word": "lukeskywalker"
  },
  {
    "type": 1,
    "word": "Luxembourg"
  },
  {
    "type": 1,
    "word": "lvmh"
  },
  {
    "type": 1,
    "word": "Macedonia"
  },
  {
    "type": 1,
    "word": "Madagascar"
  },
  {
    "type": 1,
    "word": "madonna"
  },
  {
    "type": 1,
    "word": "madrid"
  },
  {
    "type": 1,
    "word": "mahomet"
  },
  {
    "type": 1,
    "word": "Malawi"
  },
  {
    "type": 1,
    "word": "Malaysia"
  },
  {
    "type": 1,
    "word": "malboro"
  },
  {
    "type": 1,
    "word": "malcomx"
  },
  {
    "type": 1,
    "word": "Maldives"
  },
  {
    "type": 1,
    "word": "manager"
  },
  {
    "type": 1,
    "word": "manchester"
  },
  {
    "type": 1,
    "word": "mängele"
  },
  {
    "type": 1,
    "word": "mängelle"
  },
  {
    "type": 1,
    "word": "manila"
  },
  {
    "type": 1,
    "word": "maotse"
  },
  {
    "type": 1,
    "word": "maozedong"
  },
  {
    "type": 1,
    "word": "maricon"
  },
  {
    "type": 1,
    "word": "mariecurie"
  },
  {
    "type": 1,
    "word": "mariguana"
  },
  {
    "type": 1,
    "word": "marihua"
  },
  {
    "type": 1,
    "word": "marijua"
  },
  {
    "type": 1,
    "word": "marijuana"
  },
  {
    "type": 1,
    "word": "Mariposa"
  },
  {
    "type": 1,
    "word": "mariquita"
  },
  {
    "type": 1,
    "word": "marlboro"
  },
  {
    "type": 1,
    "word": "marlboro"
  },
  {
    "type": 1,
    "word": "Martinique"
  },
  {
    "type": 1,
    "word": "masturb"
  },
  {
    "type": 1,
    "word": "masturb"
  },
  {
    "type": 1,
    "word": "Mauritania"
  },
  {
    "type": 1,
    "word": "Mauritius"
  },
  {
    "type": 1,
    "word": "Mayotte"
  },
  {
    "type": 1,
    "word": "mcdonald"
  },
  {
    "type": 1,
    "word": "mcfag"
  },
  {
    "type": 1,
    "word": "meinkampf"
  },
  {
    "type": 1,
    "word": "melbourne"
  },
  {
    "type": 1,
    "word": "mercedes"
  },
  {
    "type": 1,
    "word": "methadone"
  },
  {
    "type": 1,
    "word": "Mexico"
  },
  {
    "type": 1,
    "word": "mickaeljack"
  },
  {
    "type": 1,
    "word": "Micronesia"
  },
  {
    "type": 1,
    "word": "microsoft"
  },
  {
    "type": 1,
    "word": "middleearth"
  },
  {
    "type": 1,
    "word": "minneapolis"
  },
  {
    "type": 1,
    "word": "minogue"
  },
  {
    "type": 1,
    "word": "Miquelon"
  },
  {
    "type": 1,
    "word": "mjackson"
  },
  {
    "type": 1,
    "word": "mmm"
  },
  {
    "type": 1,
    "word": "moderateur"
  },
  {
    "type": 1,
    "word": "moderator"
  },
  {
    "type": 1,
    "word": "Moldova"
  },
  {
    "type": 1,
    "word": "Monaco"
  },
  {
    "type": 1,
    "word": "Mongolia"
  },
  {
    "type": 1,
    "word": "monkeyd"
  },
  {
    "type": 1,
    "word": "Montenegro"
  },
  {
    "type": 1,
    "word": "monterey"
  },
  {
    "type": 1,
    "word": "montreal"
  },
  {
    "type": 1,
    "word": "Montserrat"
  },
  {
    "type": 1,
    "word": "Morocco"
  },
  {
    "type": 1,
    "word": "moscow"
  },
  {
    "type": 1,
    "word": "Mozambique"
  },
  {
    "type": 1,
    "word": "mozart"
  },
  {
    "type": 1,
    "word": "mtv"
  },
  {
    "type": 1,
    "word": "muffdiv"
  },
  {
    "type": 1,
    "word": "mumbai"
  },
  {
    "type": 1,
    "word": "munging"
  },
  {
    "type": 1,
    "word": "munich"
  },
  {
    "type": 1,
    "word": "murdoch"
  },
  {
    "type": 1,
    "word": "Mutterficker"
  },
  {
    "type": 1,
    "word": "Myanmar"
  },
  {
    "type": 1,
    "word": "nagoya"
  },
  {
    "type": 1,
    "word": "nambla"
  },
  {
    "type": 1,
    "word": "Namibia"
  },
  {
    "type": 1,
    "word": "napoleon"
  },
  {
    "type": 1,
    "word": "naruto"
  },
  {
    "type": 1,
    "word": "naughtydog"
  },
  {
    "type": 1,
    "word": "nazi"
  },
  {
    "type": 1,
    "word": "nazzi"
  },
  {
    "type": 1,
    "word": "ncsoft"
  },
  {
    "type": 1,
    "word": "negro"
  },
  {
    "type": 1,
    "word": "Netherlands"
  },
  {
    "type": 1,
    "word": "newbi"
  },
  {
    "type": 1,
    "word": "NewGuinea"
  },
  {
    "type": 1,
    "word": "newyork"
  },
  {
    "type": 1,
    "word": "NewZealand"
  },
  {
    "type": 1,
    "word": "nexon"
  },
  {
    "type": 1,
    "word": "Nicaragua"
  },
  {
    "type": 1,
    "word": "nicorobin"
  },
  {
    "type": 1,
    "word": "nigabo"
  },
  {
    "type": 1,
    "word": "Nigeria"
  },
  {
    "type": 1,
    "word": "nigga"
  },
  {
    "type": 1,
    "word": "nigger"
  },
  {
    "type": 1,
    "word": "niglet"
  },
  {
    "type": 1,
    "word": "nignog"
  },
  {
    "type": 1,
    "word": "nihilist"
  },
  {
    "type": 1,
    "word": "nimphom"
  },
  {
    "type": 1,
    "word": "nintendo"
  },
  {
    "type": 1,
    "word": "nintendo"
  },
  {
    "type": 1,
    "word": "nipple"
  },
  {
    "type": 1,
    "word": "nnn"
  },
  {
    "type": 1,
    "word": "noob"
  },
  {
    "type": 1,
    "word": "Norway"
  },
  {
    "type": 1,
    "word": "nutsack"
  },
  {
    "type": 1,
    "word": "nymphom"
  },
  {
    "type": 1,
    "word": "oakland"
  },
  {
    "type": 1,
    "word": "obama"
  },
  {
    "type": 1,
    "word": "obamma"
  },
  {
    "type": 1,
    "word": "obbamma"
  },
  {
    "type": 1,
    "word": "obiwan"
  },
  {
    "type": 1,
    "word": "octopussy"
  },
  {
    "type": 1,
    "word": "offline"
  },
  {
    "type": 1,
    "word": "omorashi"
  },
  {
    "type": 1,
    "word": "onepiece"
  },
  {
    "type": 1,
    "word": "onepiece"
  },
  {
    "type": 1,
    "word": "online"
  },
  {
    "type": 1,
    "word": "ooo"
  },
  {
    "type": 1,
    "word": "oprahwinfrey"
  },
  {
    "type": 1,
    "word": "orgasm"
  },
  {
    "type": 1,
    "word": "osaka"
  },
  {
    "type": 1,
    "word": "pablopicasso"
  },
  {
    "type": 1,
    "word": "paedoph"
  },
  {
    "type": 1,
    "word": "Pakistan"
  },
  {
    "type": 1,
    "word": "Palestin"
  },
  {
    "type": 1,
    "word": "Panama"
  },
  {
    "type": 1,
    "word": "panocha"
  },
  {
    "type": 1,
    "word": "panooch"
  },
  {
    "type": 1,
    "word": "Paraguay"
  },
  {
    "type": 1,
    "word": "paris"
  },
  {
    "type": 1,
    "word": "pedobear"
  },
  {
    "type": 1,
    "word": "pedoph"
  },
  {
    "type": 1,
    "word": "pegging"
  },
  {
    "type": 1,
    "word": "pepsi"
  },
  {
    "type": 1,
    "word": "perrier"
  },
  {
    "type": 1,
    "word": "petersburg"
  },
  {
    "type": 1,
    "word": "philadelph"
  },
  {
    "type": 1,
    "word": "philimorris"
  },
  {
    "type": 1,
    "word": "Philippines"
  },
  {
    "type": 1,
    "word": "Pichacorta"
  },
  {
    "type": 1,
    "word": "Picollo"
  },
  {
    "type": 1,
    "word": "picolo"
  },
  {
    "type": 1,
    "word": "picsou"
  },
  {
    "type": 1,
    "word": "pinterest"
  },
  {
    "type": 1,
    "word": "pissing"
  },
  {
    "type": 1,
    "word": "playboy"
  },
  {
    "type": 1,
    "word": "playstation"
  },
  {
    "type": 1,
    "word": "playwork"
  },
  {
    "type": 1,
    "word": "pokemon"
  },
  {
    "type": 1,
    "word": "pokkemon"
  },
  {
    "type": 1,
    "word": "Poland"
  },
  {
    "type": 1,
    "word": "polesmoker"
  },
  {
    "type": 1,
    "word": "police"
  },
  {
    "type": 1,
    "word": "polizei"
  },
  {
    "type": 1,
    "word": "pollock"
  },
  {
    "type": 1,
    "word": "Polynesia"
  },
  {
    "type": 1,
    "word": "ponyplay"
  },
  {
    "type": 1,
    "word": "poonany"
  },
  {
    "type": 1,
    "word": "poontang"
  },
  {
    "type": 1,
    "word": "popefrancis"
  },
  {
    "type": 1,
    "word": "porchmonk"
  },
  {
    "type": 1,
    "word": "porno"
  },
  {
    "type": 1,
    "word": "Portugal"
  },
  {
    "type": 1,
    "word": "ppp"
  },
  {
    "type": 1,
    "word": "president"
  },
  {
    "type": 1,
    "word": "pretoria"
  },
  {
    "type": 1,
    "word": "prophet"
  },
  {
    "type": 1,
    "word": "prostitu"
  },
  {
    "type": 1,
    "word": "protestan"
  },
  {
    "type": 1,
    "word": "psychopat"
  },
  {
    "type": 1,
    "word": "publicit"
  },
  {
    "type": 1,
    "word": "PuertoRico"
  },
  {
    "type": 1,
    "word": "punhet"
  },
  {
    "type": 1,
    "word": "pussies"
  },
  {
    "type": 1,
    "word": "putain"
  },
  {
    "type": 1,
    "word": "puzzledragons"
  },
  {
    "type": 1,
    "word": "Qatar"
  },
  {
    "type": 1,
    "word": "qqq"
  },
  {
    "type": 1,
    "word": "raghead"
  },
  {
    "type": 1,
    "word": "reagan"
  },
  {
    "type": 1,
    "word": "rectum"
  },
  {
    "type": 1,
    "word": "republican"
  },
  {
    "type": 1,
    "word": "rimjob"
  },
  {
    "type": 1,
    "word": "rimjob"
  },
  {
    "type": 1,
    "word": "riodejan"
  },
  {
    "type": 1,
    "word": "riyadh"
  },
  {
    "type": 1,
    "word": "robinhood"
  },
  {
    "type": 1,
    "word": "Romania"
  },
  {
    "type": 1,
    "word": "roosevelt"
  },
  {
    "type": 1,
    "word": "roronoa"
  },
  {
    "type": 1,
    "word": "rovio"
  },
  {
    "type": 1,
    "word": "rrr"
  },
  {
    "type": 1,
    "word": "russia"
  },
  {
    "type": 1,
    "word": "Rwanda"
  },
  {
    "type": 1,
    "word": "saddam"
  },
  {
    "type": 1,
    "word": "sadism"
  },
  {
    "type": 1,
    "word": "sadist"
  },
  {
    "type": 1,
    "word": "sadomaso"
  },
  {
    "type": 1,
    "word": "salaud"
  },
  {
    "type": 1,
    "word": "salope"
  },
  {
    "type": 1,
    "word": "Samoa"
  },
  {
    "type": 1,
    "word": "samsung"
  },
  {
    "type": 1,
    "word": "sandiego"
  },
  {
    "type": 1,
    "word": "sandnig"
  },
  {
    "type": 1,
    "word": "sanfrancisco"
  },
  {
    "type": 1,
    "word": "sangohan"
  },
  {
    "type": 1,
    "word": "sangoku"
  },
  {
    "type": 1,
    "word": "sangoten"
  },
  {
    "type": 1,
    "word": "SanMarino"
  },
  {
    "type": 1,
    "word": "sansuukyi"
  },
  {
    "type": 1,
    "word": "santaclaus"
  },
  {
    "type": 1,
    "word": "santaklaus"
  },
  {
    "type": 1,
    "word": "santorum"
  },
  {
    "type": 1,
    "word": "saopaulo"
  },
  {
    "type": 1,
    "word": "sapporo"
  },
  {
    "type": 1,
    "word": "sarahpalin"
  },
  {
    "type": 1,
    "word": "sarkozy"
  },
  {
    "type": 1,
    "word": "SaudiAra"
  },
  {
    "type": 1,
    "word": "scharzenegger"
  },
  {
    "type": 1,
    "word": "scheise"
  },
  {
    "type": 1,
    "word": "scheiss"
  },
  {
    "type": 1,
    "word": "Scheisse"
  },
  {
    "type": 1,
    "word": "scheisskopf"
  },
  {
    "type": 1,
    "word": "schlampe"
  },
  {
    "type": 1,
    "word": "schlong"
  },
  {
    "type": 1,
    "word": "schumacher"
  },
  {
    "type": 1,
    "word": "Schwanz"
  },
  {
    "type": 1,
    "word": "Scotland"
  },
  {
    "type": 1,
    "word": "scrote"
  },
  {
    "type": 1,
    "word": "Senegal"
  },
  {
    "type": 1,
    "word": "Serbia"
  },
  {
    "type": 1,
    "word": "Seychelles"
  },
  {
    "type": 1,
    "word": "shakira"
  },
  {
    "type": 1,
    "word": "shanghai"
  },
  {
    "type": 1,
    "word": "shanks"
  },
  {
    "type": 1,
    "word": "shemal"
  },
  {
    "type": 1,
    "word": "shenyang"
  },
  {
    "type": 1,
    "word": "shenzhen"
  },
  {
    "type": 1,
    "word": "shichibukai"
  },
  {
    "type": 1,
    "word": "shitas"
  },
  {
    "type": 1,
    "word": "shithole"
  },
  {
    "type": 1,
    "word": "shitlover"
  },
  {
    "type": 1,
    "word": "shitter"
  },
  {
    "type": 1,
    "word": "shitting"
  },
  {
    "type": 1,
    "word": "shrimping"
  },
  {
    "type": 1,
    "word": "SierraLeone"
  },
  {
    "type": 1,
    "word": "sikhism"
  },
  {
    "type": 1,
    "word": "Singapore"
  },
  {
    "type": 1,
    "word": "singapore"
  },
  {
    "type": 1,
    "word": "skype"
  },
  {
    "type": 1,
    "word": "slanteye"
  },
  {
    "type": 1,
    "word": "Slovakia"
  },
  {
    "type": 1,
    "word": "Slovenia"
  },
  {
    "type": 1,
    "word": "smiirnof"
  },
  {
    "type": 1,
    "word": "smirnof"
  },
  {
    "type": 1,
    "word": "sodom"
  },
  {
    "type": 1,
    "word": "sodom"
  },
  {
    "type": 1,
    "word": "sogeking"
  },
  {
    "type": 1,
    "word": "soixanteneuf"
  },
  {
    "type": 1,
    "word": "Somalia"
  },
  {
    "type": 1,
    "word": "sony"
  },
  {
    "type": 1,
    "word": "soundcloud"
  },
  {
    "type": 1,
    "word": "SouthAfrica"
  },
  {
    "type": 1,
    "word": "SouthSudan"
  },
  {
    "type": 1,
    "word": "soviet"
  },
  {
    "type": 1,
    "word": "Spain"
  },
  {
    "type": 1,
    "word": "spanking"
  },
  {
    "type": 1,
    "word": "sperma"
  },
  {
    "type": 1,
    "word": "spermalecker"
  },
  {
    "type": 1,
    "word": "spermalover"
  },
  {
    "type": 1,
    "word": "spermazoid"
  },
  {
    "type": 1,
    "word": "spermlover"
  },
  {
    "type": 1,
    "word": "spermlover"
  },
  {
    "type": 1,
    "word": "sphincter"
  },
  {
    "type": 1,
    "word": "spiderman"
  },
  {
    "type": 1,
    "word": "splooge"
  },
  {
    "type": 1,
    "word": "spooge"
  },
  {
    "type": 1,
    "word": "spotify"
  },
  {
    "type": 1,
    "word": "squirting"
  },
  {
    "type": 1,
    "word": "SriLanka"
  },
  {
    "type": 1,
    "word": "sss"
  },
  {
    "type": 1,
    "word": "staline"
  },
  {
    "type": 1,
    "word": "stalline"
  },
  {
    "type": 1,
    "word": "stalone"
  },
  {
    "type": 1,
    "word": "starbucks"
  },
  {
    "type": 1,
    "word": "starcraft"
  },
  {
    "type": 1,
    "word": "statesofam"
  },
  {
    "type": 1,
    "word": "stephenking"
  },
  {
    "type": 1,
    "word": "stevejobs"
  },
  {
    "type": 1,
    "word": "stevenspielberg"
  },
  {
    "type": 1,
    "word": "strappado"
  },
  {
    "type": 1,
    "word": "sucka"
  },
  {
    "type": 1,
    "word": "sumqayit"
  },
  {
    "type": 1,
    "word": "supercell"
  },
  {
    "type": 1,
    "word": "supergirl"
  },
  {
    "type": 1,
    "word": "superman"
  },
  {
    "type": 1,
    "word": "Suriname"
  },
  {
    "type": 1,
    "word": "suxx"
  },
  {
    "type": 1,
    "word": "suxxx"
  },
  {
    "type": 1,
    "word": "swastika"
  },
  {
    "type": 1,
    "word": "Swaziland"
  },
  {
    "type": 1,
    "word": "Sweden"
  },
  {
    "type": 1,
    "word": "Switzerland"
  },
  {
    "type": 1,
    "word": "sydney"
  },
  {
    "type": 1,
    "word": "taipei"
  },
  {
    "type": 1,
    "word": "Taiwan"
  },
  {
    "type": 1,
    "word": "Tajikistan"
  },
  {
    "type": 1,
    "word": "taleban"
  },
  {
    "type": 1,
    "word": "taliban"
  },
  {
    "type": 1,
    "word": "tantouse"
  },
  {
    "type": 1,
    "word": "tantouze"
  },
  {
    "type": 1,
    "word": "Tanzania"
  },
  {
    "type": 1,
    "word": "taoism"
  },
  {
    "type": 1,
    "word": "tarlouze"
  },
  {
    "type": 1,
    "word": "tashkent"
  },
  {
    "type": 1,
    "word": "teamgm"
  },
  {
    "type": 1,
    "word": "teenforte"
  },
  {
    "type": 1,
    "word": "teenonte"
  },
  {
    "type": 1,
    "word": "teensforte"
  },
  {
    "type": 1,
    "word": "teensonte"
  },
  {
    "type": 1,
    "word": "tehran"
  },
  {
    "type": 1,
    "word": "tenriis"
  },
  {
    "type": 1,
    "word": "tequila"
  },
  {
    "type": 1,
    "word": "terorist"
  },
  {
    "type": 1,
    "word": "terorrist"
  },
  {
    "type": 1,
    "word": "terrorist"
  },
  {
    "type": 1,
    "word": "terrorrist"
  },
  {
    "type": 1,
    "word": "testicle"
  },
  {
    "type": 1,
    "word": "testicul"
  },
  {
    "type": 1,
    "word": "Thailand"
  },
  {
    "type": 1,
    "word": "thatcher"
  },
  {
    "type": 1,
    "word": "thedonald"
  },
  {
    "type": 1,
    "word": "theflash"
  },
  {
    "type": 1,
    "word": "thehobbit"
  },
  {
    "type": 1,
    "word": "throating"
  },
  {
    "type": 1,
    "word": "tianjin"
  },
  {
    "type": 1,
    "word": "tigerwoods"
  },
  {
    "type": 1,
    "word": "TimorLes"
  },
  {
    "type": 1,
    "word": "titandass"
  },
  {
    "type": 1,
    "word": "Tokelau"
  },
  {
    "type": 1,
    "word": "tokyo"
  },
  {
    "type": 1,
    "word": "tolkien"
  },
  {
    "type": 1,
    "word": "tolstoy"
  },
  {
    "type": 1,
    "word": "tomcruise"
  },
  {
    "type": 1,
    "word": "tontopollas"
  },
  {
    "type": 1,
    "word": "tonychopper"
  },
  {
    "type": 1,
    "word": "tonymontana"
  },
  {
    "type": 1,
    "word": "toronto"
  },
  {
    "type": 1,
    "word": "towelhead"
  },
  {
    "type": 1,
    "word": "tranny"
  },
  {
    "type": 1,
    "word": "transformers"
  },
  {
    "type": 1,
    "word": "Trinidad"
  },
  {
    "type": 1,
    "word": "trotsky"
  },
  {
    "type": 1,
    "word": "trouducul"
  },
  {
    "type": 1,
    "word": "trouducul"
  },
  {
    "type": 1,
    "word": "ttt"
  },
  {
    "type": 1,
    "word": "tubgirl"
  },
  {
    "type": 1,
    "word": "tumblr"
  },
  {
    "type": 1,
    "word": "Tunisia"
  },
  {
    "type": 1,
    "word": "Turkey"
  },
  {
    "type": 1,
    "word": "Turkmenistan"
  },
  {
    "type": 1,
    "word": "tushy"
  },
  {
    "type": 1,
    "word": "Tuvalu"
  },
  {
    "type": 1,
    "word": "twatlip"
  },
  {
    "type": 1,
    "word": "twatw"
  },
  {
    "type": 1,
    "word": "twintowers"
  },
  {
    "type": 1,
    "word": "twitter"
  },
  {
    "type": 1,
    "word": "Uganda"
  },
  {
    "type": 1,
    "word": "Ukraine"
  },
  {
    "type": 1,
    "word": "UnitedKi"
  },
  {
    "type": 1,
    "word": "unitedstates"
  },
  {
    "type": 1,
    "word": "urethra"
  },
  {
    "type": 1,
    "word": "urophil"
  },
  {
    "type": 1,
    "word": "Uruguay"
  },
  {
    "type": 1,
    "word": "usainbolt"
  },
  {
    "type": 1,
    "word": "uuu"
  },
  {
    "type": 1,
    "word": "Uzbekistan"
  },
  {
    "type": 1,
    "word": "vagina"
  },
  {
    "type": 1,
    "word": "vagita"
  },
  {
    "type": 1,
    "word": "vajayjay"
  },
  {
    "type": 1,
    "word": "vancouver"
  },
  {
    "type": 1,
    "word": "vangogh"
  },
  {
    "type": 1,
    "word": "Vanuatu"
  },
  {
    "type": 1,
    "word": "velhaco"
  },
  {
    "type": 1,
    "word": "Venezuela"
  },
  {
    "type": 1,
    "word": "viagra"
  },
  {
    "type": 1,
    "word": "vibratoren"
  },
  {
    "type": 1,
    "word": "vibromasseur"
  },
  {
    "type": 1,
    "word": "Vietnam"
  },
  {
    "type": 1,
    "word": "violeur"
  },
  {
    "type": 1,
    "word": "vivendi"
  },
  {
    "type": 1,
    "word": "vjayjay"
  },
  {
    "type": 1,
    "word": "vodka"
  },
  {
    "type": 1,
    "word": "volunteer"
  },
  {
    "type": 1,
    "word": "vorareph"
  },
  {
    "type": 1,
    "word": "vulva"
  },
  {
    "type": 1,
    "word": "vulva"
  },
  {
    "type": 1,
    "word": "vvv"
  },
  {
    "type": 1,
    "word": "walmart"
  },
  {
    "type": 1,
    "word": "wank"
  },
  {
    "type": 1,
    "word": "wanker"
  },
  {
    "type": 1,
    "word": "warcraft"
  },
  {
    "type": 1,
    "word": "warhammer"
  },
  {
    "type": 1,
    "word": "washington"
  },
  {
    "type": 1,
    "word": "weed"
  },
  {
    "type": 1,
    "word": "wetback"
  },
  {
    "type": 1,
    "word": "whatsapp"
  },
  {
    "type": 1,
    "word": "whiskey"
  },
  {
    "type": 1,
    "word": "whisky"
  },
  {
    "type": 1,
    "word": "whitebeard"
  },
  {
    "type": 1,
    "word": "whitepow"
  },
  {
    "type": 1,
    "word": "whitewid"
  },
  {
    "type": 1,
    "word": "whore"
  },
  {
    "type": 1,
    "word": "whore"
  },
  {
    "type": 1,
    "word": "Wichser"
  },
  {
    "type": 1,
    "word": "willsmith"
  },
  {
    "type": 1,
    "word": "windowsvista"
  },
  {
    "type": 1,
    "word": "windowsxp"
  },
  {
    "type": 1,
    "word": "winfree"
  },
  {
    "type": 1,
    "word": "wolverin"
  },
  {
    "type": 1,
    "word": "wonderwoman"
  },
  {
    "type": 1,
    "word": "www"
  },
  {
    "type": 1,
    "word": "xbox"
  },
  {
    "type": 1,
    "word": "xbox"
  },
  {
    "type": 1,
    "word": "xxx"
  },
  {
    "type": 1,
    "word": "Yemen"
  },
  {
    "type": 1,
    "word": "yiffy"
  },
  {
    "type": 1,
    "word": "youaregay"
  },
  {
    "type": 1,
    "word": "yourgay"
  },
  {
    "type": 1,
    "word": "youtube"
  },
  {
    "type": 1,
    "word": "yyy"
  },
  {
    "type": 1,
    "word": "Zambia"
  },
  {
    "type": 1,
    "word": "Zimbabwe"
  },
  {
    "type": 1,
    "word": "zipperhead"
  },
  {
    "type": 1,
    "word": "zooph"
  },
  {
    "type": 1,
    "word": "zoophil"
  },
  {
    "type": 1,
    "word": "zorro"
  },
  {
    "type": 1,
    "word": "zzz"
  },
  {
    "type": 1,
    "word": "ganja"
  },
  {
    "type": 1,
    "word": "weed"
  },
  {
    "type": 1,
    "word": "sativa"
  },
  {
    "type": 1,
    "word": "marijuana"
  },
  {
    "type": 1,
    "word": "cannabis"
  },
  {
    "type": 1,
    "word": "hashich"
  },
  {
    "type": 1,
    "word": "hashish"
  },
  {
    "type": 1,
    "word": "sativa"
  },
  {
    "type": 1,
    "word": "indica"
  },
  {
    "type": 1,
    "word": "ruderalis"
  },
  {
    "type": 1,
    "word": "developer"
  },
  {
    "type": 1,
    "word": "develop"
  },
  {
    "type": 1,
    "word": "madrigal"
  },
  {
    "type": 1,
    "word": "aibatt"
  },
  {
    "type": 1,
    "word": "lawolf"
  },
  {
    "type": 1,
    "word": "flyforfun"
  },
  {
    "type": 1,
    "word": "prankster"
  },
  {
    "type": 1,
    "word": "ivillis"
  },
  {
    "type": 1,
    "word": "rhisis"
  },
  {
    "type": 1,
    "word": "jaken"
  },
  {
    "type": 1,
    "word": "astaroth"
  },
  {
    "type": 1,
    "word": "flarine"
  },
  {
    "type": 1,
    "word": "flaris"
  },
  {
    "type": 1,
    "word": "darkon"
  },
  {
    "type": 1,
    "word": "shaduwar"
  },
  {
    "type": 1,
    "word": "bukake"
  },
  {
    "type": 1,
    "word": "mushpang"
  },
  {
    "type": 1,
    "word": "burudeng"
  },
  {
    "type": 1,
    "word": "pukepuke"
  },
  {
    "type": 1,
    "word": "peakyturtle"
  },
  {
    "type": 1,
    "word": "nyangnyang"
  },
  {
    "type": 1,
    "word": "fefern"
  },
  {
    "type": 1,
    "word": "wagsaac"
  },
  {
    "type": 1,
    "word": "masquerpet"
  },
  {
    "type": 1,
    "word": "crohell"
  },
  {
    "type": 1,
    "word": "bukhen"
  },
  {
    "type": 1,
    "word": "toadrin"
  },
  {
    "type": 1,
    "word": "Flbyrigen"
  },
  {
    "type": 1,
    "word": "Kyouchish"
  },
  {
    "type": 1,
    "word": "Kanonicus"
  },
  {
    "type": 1,
    "word": "Mercenary"
  },
  {
    "type": 1,
    "word": "Acrobat"
  },
  {
    "type": 1,
    "word": "Magician"
  },
  {
    "type": 1,
    "word": "Billposter"
  },
  {
    "type": 1,
    "word": "Ringmaster"
  },
  {
    "type": 1,
    "word": "Jester"
  },
  {
    "type": 1,
    "word": "Psykeeper"
  },
  {
    "type": 1,
    "word": "Harlequin"
  },
  {
    "type": 1,
    "word": "Crackshooter"
  },
  {
    "type": 1,
    "word": "Arcanist"
  },
  {
    "type": 1,
    "word": "Templar"
  },
  {
    "type": 1,
    "word": "Forcemaster"
  },
  {
    "type": 1,
    "word": "Mentalist"
  },
  {
    "type": 1,
    "word": "Meteonyker"
  },
  {
    "type": 1,
    "word": "clockwork"
  },
  {
    "type": 1,
    "word": "rangda"
  },
  {
    "type": 1,
    "word": "redmantis"
  },
  {
    "type": 1,
    "word": "mokomoci"
  },
  {
    "type": 1,
    "word": "bobochan"
  },
  {
    "type": 1,
    "word": "boboku"
  },
  {
    "type": 1,
    "word": "donaris"
  },
  {
    "type": 1,
    "word": "ryupang"
  },
  {
    "type": 1,
    "word": "teshar"
  },
  {
    "type": 1,
    "word": "nomier"
  },
  {
    "type": 1,
    "word": "langdrong"
  },
  {
    "type": 1,
    "word": "Clackcable"
  },
  {
    "type": 1,
    "word": "Mikyel"
  },
  {
    "type": 2,
    "word": ".com"
  },
  {
    "type": 2,
    "word": "4r5e"
  },
  {
    "type": 2,
    "word": "5h1t"
  },
  {
    "type": 2,
    "word": "acrotomoph"
  },
  {
    "type": 2,
    "word": "ahole"
  },
  {
    "type": 2,
    "word": "analsex"
  },
  {
    "type": 2,
    "word": "aniling"
  },
  {
    "type": 2,
    "word": "anuman"
  },
  {
    "type": 2,
    "word": "apeshit"
  },
  {
    "type": 2,
    "word": "ar5e"
  },
  {
    "type": 2,
    "word": "Arschficker"
  },
  {
    "type": 2,
    "word": "Arschgeige"
  },
  {
    "type": 2,
    "word": "Arschgesicht"
  },
  {
    "type": 2,
    "word": "Arschloch"
  },
  {
    "type": 2,
    "word": "arsehol"
  },
  {
    "type": 2,
    "word": "askhole"
  },
  {
    "type": 2,
    "word": "assbag"
  },
  {
    "type": 2,
    "word": "assbandit"
  },
  {
    "type": 2,
    "word": "assbanger"
  },
  {
    "type": 2,
    "word": "assberge"
  },
  {
    "type": 2,
    "word": "assbite"
  },
  {
    "type": 2,
    "word": "assburge"
  },
  {
    "type": 2,
    "word": "assclown"
  },
  {
    "type": 2,
    "word": "asscock"
  },
  {
    "type": 2,
    "word": "asscrack"
  },
  {
    "type": 2,
    "word": "assface"
  },
  {
    "type": 2,
    "word": "assface"
  },
  {
    "type": 2,
    "word": "assgoblin"
  },
  {
    "type": 2,
    "word": "asshat"
  },
  {
    "type": 2,
    "word": "asshead"
  },
  {
    "type": 2,
    "word": "asshole"
  },
  {
    "type": 2,
    "word": "assjacker"
  },
  {
    "type": 2,
    "word": "asslick"
  },
  {
    "type": 2,
    "word": "assmonk"
  },
  {
    "type": 2,
    "word": "assmunch"
  },
  {
    "type": 2,
    "word": "asspira"
  },
  {
    "type": 2,
    "word": "assrap"
  },
  {
    "type": 2,
    "word": "asssh"
  },
  {
    "type": 2,
    "word": "asssuc"
  },
  {
    "type": 2,
    "word": "asswad"
  },
  {
    "type": 2,
    "word": "asswipe"
  },
  {
    "type": 2,
    "word": "b!tch"
  },
  {
    "type": 2,
    "word": "ballsack"
  },
  {
    "type": 2,
    "word": "bampot"
  },
  {
    "type": 2,
    "word": "bangbros"
  },
  {
    "type": 2,
    "word": "barebac"
  },
  {
    "type": 2,
    "word": "bastardo"
  },
  {
    "type": 2,
    "word": "bastinado"
  },
  {
    "type": 2,
    "word": "bcunt"
  },
  {
    "type": 2,
    "word": "bdsm"
  },
  {
    "type": 2,
    "word": "beaner"
  },
  {
    "type": 2,
    "word": "biatch"
  },
  {
    "type": 2,
    "word": "biitch"
  },
  {
    "type": 2,
    "word": "binibroc"
  },
  {
    "type": 2,
    "word": "bitch"
  },
  {
    "type": 2,
    "word": "blch"
  },
  {
    "type": 2,
    "word": "b1itch"
  },
  {
    "type": 2,
    "word": "blltch"
  },
  {
    "type": 2,
    "word": "blowjob"
  },
  {
    "type": 2,
    "word": "blumpkin"
  },
  {
    "type": 2,
    "word": "bollock"
  },
  {
    "type": 2,
    "word": "bollok"
  },
  {
    "type": 2,
    "word": "bollox"
  },
  {
    "type": 2,
    "word": "boob"
  },
  {
    "type": 2,
    "word": "boy2boy"
  },
  {
    "type": 2,
    "word": "boy4boy"
  },
  {
    "type": 2,
    "word": "boyonboy"
  },
  {
    "type": 2,
    "word": "boys2boys"
  },
  {
    "type": 2,
    "word": "boys4boys"
  },
  {
    "type": 2,
    "word": "boysforboy"
  },
  {
    "type": 2,
    "word": "boysonboys"
  },
  {
    "type": 2,
    "word": "branler"
  },
  {
    "type": 2,
    "word": "brothel"
  },
  {
    "type": 2,
    "word": "bshit"
  },
  {
    "type": 2,
    "word": "bugger"
  },
  {
    "type": 2,
    "word": "bukake"
  },
  {
    "type": 2,
    "word": "bukkake"
  },
  {
    "type": 2,
    "word": "bulldyke"
  },
  {
    "type": 2,
    "word": "bullshit"
  },
  {
    "type": 2,
    "word": "bunghole"
  },
  {
    "type": 2,
    "word": "buttcheeks"
  },
  {
    "type": 2,
    "word": "butthole"
  },
  {
    "type": 2,
    "word": "buttplug"
  },
  {
    "type": 2,
    "word": "buwisit"
  },
  {
    "type": 2,
    "word": "bwiset"
  },
  {
    "type": 2,
    "word": "c0ck"
  },
  {
    "type": 2,
    "word": "calientapollas"
  },
  {
    "type": 2,
    "word": "cameltoe"
  },
  {
    "type": 2,
    "word": "camgirl"
  },
  {
    "type": 2,
    "word": "camslut"
  },
  {
    "type": 2,
    "word": "caralho"
  },
  {
    "type": 2,
    "word": "carpetmuncher"
  },
  {
    "type": 2,
    "word": "chesticle"
  },
  {
    "type": 2,
    "word": "chimba"
  },
  {
    "type": 2,
    "word": "chinc"
  },
  {
    "type": 2,
    "word": "chinga"
  },
  {
    "type": 2,
    "word": "chink"
  },
  {
    "type": 2,
    "word": "choad"
  },
  {
    "type": 2,
    "word": "chode"
  },
  {
    "type": 2,
    "word": "Chupame"
  },
  {
    "type": 2,
    "word": "chuparola"
  },
  {
    "type": 2,
    "word": "circlejerk"
  },
  {
    "type": 2,
    "word": "cl1t"
  },
  {
    "type": 2,
    "word": "clitface"
  },
  {
    "type": 2,
    "word": "clitoris"
  },
  {
    "type": 2,
    "word": "cockass"
  },
  {
    "type": 2,
    "word": "cockbite"
  },
  {
    "type": 2,
    "word": "cockburg"
  },
  {
    "type": 2,
    "word": "cockface"
  },
  {
    "type": 2,
    "word": "cockhead"
  },
  {
    "type": 2,
    "word": "cockj"
  },
  {
    "type": 2,
    "word": "cockk"
  },
  {
    "type": 2,
    "word": "cockm"
  },
  {
    "type": 2,
    "word": "cockno"
  },
  {
    "type": 2,
    "word": "cocknu"
  },
  {
    "type": 2,
    "word": "cocksm"
  },
  {
    "type": 2,
    "word": "cocksn"
  },
  {
    "type": 2,
    "word": "cocksuc"
  },
  {
    "type": 2,
    "word": "cockwa"
  },
  {
    "type": 2,
    "word": "Cojonazos"
  },
  {
    "type": 2,
    "word": "conasse"
  },
  {
    "type": 2,
    "word": "connard"
  },
  {
    "type": 2,
    "word": "cooch"
  },
  {
    "type": 2,
    "word": "coprolagnia"
  },
  {
    "type": 2,
    "word": "coproph"
  },
  {
    "type": 2,
    "word": "cornhole"
  },
  {
    "type": 2,
    "word": "couilles"
  },
  {
    "type": 2,
    "word": "cowgirl"
  },
  {
    "type": 2,
    "word": "creampie"
  },
  {
    "type": 2,
    "word": "cumbub"
  },
  {
    "type": 2,
    "word": "cumdump"
  },
  {
    "type": 2,
    "word": "cumfac"
  },
  {
    "type": 2,
    "word": "cumguz"
  },
  {
    "type": 2,
    "word": "cumjoc"
  },
  {
    "type": 2,
    "word": "cumming"
  },
  {
    "type": 2,
    "word": "cumonmyface"
  },
  {
    "type": 2,
    "word": "cumslut"
  },
  {
    "type": 2,
    "word": "cumtart"
  },
  {
    "type": 2,
    "word": "cunnie"
  },
  {
    "type": 2,
    "word": "cunnilin"
  },
  {
    "type": 2,
    "word": "cunt"
  },
  {
    "type": 2,
    "word": "daech"
  },
  {
    "type": 2,
    "word": "Dalawa"
  },
  {
    "type": 2,
    "word": "daterape"
  },
  {
    "type": 2,
    "word": "deepthroat"
  },
  {
    "type": 2,
    "word": "deggo"
  },
  {
    "type": 2,
    "word": "degung"
  },
  {
    "type": 2,
    "word": "dendroph"
  },
  {
    "type": 2,
    "word": "Desgraciado"
  },
  {
    "type": 2,
    "word": "didilain"
  },
  {
    "type": 2,
    "word": "dike"
  },
  {
    "type": 2,
    "word": "dildo"
  },
  {
    "type": 2,
    "word": "dipshit"
  },
  {
    "type": 2,
    "word": "Diyan"
  },
  {
    "type": 2,
    "word": "doggiesty"
  },
  {
    "type": 2,
    "word": "doggysty"
  },
  {
    "type": 2,
    "word": "dolcett"
  },
  {
    "type": 2,
    "word": "dookie"
  },
  {
    "type": 2,
    "word": "doucheb"
  },
  {
    "type": 2,
    "word": "douchef"
  },
  {
    "type": 2,
    "word": "douchew"
  },
  {
    "type": 2,
    "word": "Drecksau"
  },
  {
    "type": 2,
    "word": "dumass"
  },
  {
    "type": 2,
    "word": "dumbass"
  },
  {
    "type": 2,
    "word": "dumbsh"
  },
  {
    "type": 2,
    "word": "dumsh"
  },
  {
    "type": 2,
    "word": "dyke"
  },
  {
    "type": 2,
    "word": "ejacul"
  },
  {
    "type": 2,
    "word": "ejakul"
  },
  {
    "type": 2,
    "word": "enculer"
  },
  {
    "type": 2,
    "word": "escroto"
  },
  {
    "type": 2,
    "word": "eunuch"
  },
  {
    "type": 2,
    "word": "fagbag"
  },
  {
    "type": 2,
    "word": "faggit"
  },
  {
    "type": 2,
    "word": "faggot"
  },
  {
    "type": 2,
    "word": "faghag"
  },
  {
    "type": 2,
    "word": "fagtard"
  },
  {
    "type": 2,
    "word": "fannyflap"
  },
  {
    "type": 2,
    "word": "fatass"
  },
  {
    "type": 2,
    "word": "fcuk"
  },
  {
    "type": 2,
    "word": "fcuk"
  },
  {
    "type": 2,
    "word": "fecal"
  },
  {
    "type": 2,
    "word": "felch"
  },
  {
    "type": 2,
    "word": "fellat"
  },
  {
    "type": 2,
    "word": "feltch"
  },
  {
    "type": 2,
    "word": "femdom"
  },
  {
    "type": 2,
    "word": "figging"
  },
  {
    "type": 2,
    "word": "filsdepute"
  },
  {
    "type": 2,
    "word": "fingerbang"
  },
  {
    "type": 2,
    "word": "fingering"
  },
  {
    "type": 2,
    "word": "fisting"
  },
  {
    "type": 2,
    "word": "footjob"
  },
  {
    "type": 2,
    "word": "Fotze"
  },
  {
    "type": 2,
    "word": "frotting"
  },
  {
    "type": 2,
    "word": "fuccc"
  },
  {
    "type": 2,
    "word": "fucck"
  },
  {
    "type": 2,
    "word": "fuck"
  },
  {
    "type": 2,
    "word": "fudgepacker"
  },
  {
    "type": 2,
    "word": "fukk"
  },
  {
    "type": 2,
    "word": "fuucc"
  },
  {
    "type": 2,
    "word": "fuuck"
  },
  {
    "type": 2,
    "word": "fuukk"
  },
  {
    "type": 2,
    "word": "fuuuc"
  },
  {
    "type": 2,
    "word": "fuuuk"
  },
  {
    "type": 2,
    "word": "fvck"
  },
  {
    "type": 2,
    "word": "gangbang"
  },
  {
    "type": 2,
    "word": "gayass"
  },
  {
    "type": 2,
    "word": "gaybob"
  },
  {
    "type": 2,
    "word": "gaydo"
  },
  {
    "type": 2,
    "word": "gaylord"
  },
  {
    "type": 2,
    "word": "gaytard"
  },
  {
    "type": 2,
    "word": "gaywad"
  },
  {
    "type": 2,
    "word": "genitals"
  },
  {
    "type": 2,
    "word": "Gilipollas"
  },
  {
    "type": 2,
    "word": "goatcx"
  },
  {
    "type": 2,
    "word": "goatse"
  },
  {
    "type": 2,
    "word": "gokkun"
  },
  {
    "type": 2,
    "word": "gooch"
  },
  {
    "type": 2,
    "word": "goodpoop"
  },
  {
    "type": 2,
    "word": "gook"
  },
  {
    "type": 2,
    "word": "goregasm"
  },
  {
    "type": 2,
    "word": "gringo"
  },
  {
    "type": 2,
    "word": "gspot"
  },
  {
    "type": 2,
    "word": "gudnayt"
  },
  {
    "type": 2,
    "word": "guido"
  },
  {
    "type": 2,
    "word": "handjob"
  },
  {
    "type": 2,
    "word": "harapan"
  },
  {
    "type": 2,
    "word": "hayaan"
  },
  {
    "type": 2,
    "word": "heeb"
  },
  {
    "type": 2,
    "word": "hiitler"
  },
  {
    "type": 2,
    "word": "hinayupa"
  },
  {
    "type": 2,
    "word": "hitler"
  },
  {
    "type": 2,
    "word": "honkey"
  },
  {
    "type": 2,
    "word": "hooker"
  },
  {
    "type": 2,
    "word": "humping"
  },
  {
    "type": 2,
    "word": "Hurensohn "
  },
  {
    "type": 2,
    "word": "huwag"
  },
  {
    "type": 2,
    "word": "ikaw"
  },
  {
    "type": 2,
    "word": "iniibig"
  },
  {
    "type": 2,
    "word": "iniirog"
  },
  {
    "type": 2,
    "word": "iwanan"
  },
  {
    "type": 2,
    "word": "jackass"
  },
  {
    "type": 2,
    "word": "jagoff"
  },
  {
    "type": 2,
    "word": "jerkass"
  },
  {
    "type": 2,
    "word": "jerkoff"
  },
  {
    "type": 2,
    "word": "jigaboo"
  },
  {
    "type": 2,
    "word": "jiggaboo"
  },
  {
    "type": 2,
    "word": "jiggerboo"
  },
  {
    "type": 2,
    "word": "jizz"
  },
  {
    "type": 2,
    "word": "juggs"
  },
  {
    "type": 2,
    "word": "jungleb"
  },
  {
    "type": 2,
    "word": "kaarawan"
  },
  {
    "type": 2,
    "word": "Kailan"
  },
  {
    "type": 2,
    "word": "Kaliwa"
  },
  {
    "type": 2,
    "word": "kamusta"
  },
  {
    "type": 2,
    "word": "Kanan"
  },
  {
    "type": 2,
    "word": "kasilya"
  },
  {
    "type": 2,
    "word": "kike"
  },
  {
    "type": 2,
    "word": "kinagagalak"
  },
  {
    "type": 2,
    "word": "kinkster"
  },
  {
    "type": 2,
    "word": "klux"
  },
  {
    "type": 2,
    "word": "knobbing"
  },
  {
    "type": 2,
    "word": "knobend"
  },
  {
    "type": 2,
    "word": "kooch"
  },
  {
    "type": 2,
    "word": "kraut"
  },
  {
    "type": 2,
    "word": "kunt"
  },
  {
    "type": 2,
    "word": "kyke"
  },
  {
    "type": 2,
    "word": "lameass"
  },
  {
    "type": 2,
    "word": "lardass"
  },
  {
    "type": 2,
    "word": "lengguahe"
  },
  {
    "type": 2,
    "word": "lesbo"
  },
  {
    "type": 2,
    "word": "lezzie"
  },
  {
    "type": 2,
    "word": "lubuyan"
  },
  {
    "type": 2,
    "word": "lumayas"
  },
  {
    "type": 2,
    "word": "lunukin"
  },
  {
    "type": 2,
    "word": "m1lf"
  },
  {
    "type": 2,
    "word": "mabuha"
  },
  {
    "type": 2,
    "word": "Mabuti"
  },
  {
    "type": 2,
    "word": "Maganda"
  },
  {
    "type": 2,
    "word": "magandang"
  },
  {
    "type": 2,
    "word": "magbaba"
  },
  {
    "type": 2,
    "word": "Magkano"
  },
  {
    "type": 2,
    "word": "magkantu"
  },
  {
    "type": 2,
    "word": "magpaga"
  },
  {
    "type": 2,
    "word": "magsik"
  },
  {
    "type": 2,
    "word": "magsumika"
  },
  {
    "type": 2,
    "word": "makilala"
  },
  {
    "type": 2,
    "word": "Malamig"
  },
  {
    "type": 2,
    "word": "maligayang"
  },
  {
    "type": 2,
    "word": "Maliit"
  },
  {
    "type": 2,
    "word": "manigon"
  },
  {
    "type": 2,
    "word": "maraming"
  },
  {
    "type": 2,
    "word": "maricon"
  },
  {
    "type": 2,
    "word": "Mariposa"
  },
  {
    "type": 2,
    "word": "mariquita"
  },
  {
    "type": 2,
    "word": "masturb"
  },
  {
    "type": 2,
    "word": "matulog"
  },
  {
    "type": 2,
    "word": "matutulog"
  },
  {
    "type": 2,
    "word": "mayabang"
  },
  {
    "type": 2,
    "word": "mcfag"
  },
  {
    "type": 2,
    "word": "milf"
  },
  {
    "type": 2,
    "word": "minamah"
  },
  {
    "type": 2,
    "word": "muffdiv"
  },
  {
    "type": 2,
    "word": "munging"
  },
  {
    "type": 2,
    "word": "mussolini"
  },
  {
    "type": 2,
    "word": "Mutterficker"
  },
  {
    "type": 2,
    "word": "nagkita"
  },
  {
    "type": 2,
    "word": "nagsasa"
  },
  {
    "type": 2,
    "word": "naiintin"
  },
  {
    "type": 2,
    "word": "nakakabur"
  },
  {
    "type": 2,
    "word": "nambla"
  },
  {
    "type": 2,
    "word": "naninig"
  },
  {
    "type": 2,
    "word": "nazi"
  },
  {
    "type": 2,
    "word": "negro"
  },
  {
    "type": 2,
    "word": "nigab"
  },
  {
    "type": 2,
    "word": "nigga"
  },
  {
    "type": 2,
    "word": "nigger"
  },
  {
    "type": 2,
    "word": "niglet"
  },
  {
    "type": 2,
    "word": "nignog"
  },
  {
    "type": 2,
    "word": "niikka"
  },
  {
    "type": 2,
    "word": "nikka"
  },
  {
    "type": 2,
    "word": "nimphom"
  },
  {
    "type": 2,
    "word": "nipple"
  },
  {
    "type": 2,
    "word": "noob"
  },
  {
    "type": 2,
    "word": "nutsack"
  },
  {
    "type": 2,
    "word": "nymphom"
  },
  {
    "type": 2,
    "word": "octopussy"
  },
  {
    "type": 2,
    "word": "okaygoods"
  },
  {
    "type": 2,
    "word": "omorashi"
  },
  {
    "type": 2,
    "word": "Paalam"
  },
  {
    "type": 2,
    "word": "Paálam"
  },
  {
    "type": 2,
    "word": "Paano"
  },
  {
    "type": 2,
    "word": "paedoph"
  },
  {
    "type": 2,
    "word": "pagbuti"
  },
  {
    "type": 2,
    "word": "pagdating"
  },
  {
    "type": 2,
    "word": "paglala"
  },
  {
    "type": 2,
    "word": "pagpalain"
  },
  {
    "type": 2,
    "word": "pakialama"
  },
  {
    "type": 2,
    "word": "pakingshet"
  },
  {
    "type": 2,
    "word": "Pakiú"
  },
  {
    "type": 2,
    "word": "pakshet"
  },
  {
    "type": 2,
    "word": "pangalan"
  },
  {
    "type": 2,
    "word": "panocha"
  },
  {
    "type": 2,
    "word": "panooch"
  },
  {
    "type": 2,
    "word": "paumanhin"
  },
  {
    "type": 2,
    "word": "pecker"
  },
  {
    "type": 2,
    "word": "pedob"
  },
  {
    "type": 2,
    "word": "pedoph"
  },
  {
    "type": 2,
    "word": "pegging"
  },
  {
    "type": 2,
    "word": "penis"
  },
  {
    "type": 2,
    "word": "Pichacorta"
  },
  {
    "type": 2,
    "word": "pissf"
  },
  {
    "type": 2,
    "word": "pissing"
  },
  {
    "type": 2,
    "word": "pissp"
  },
  {
    "type": 2,
    "word": "polesmoker"
  },
  {
    "type": 2,
    "word": "polloc"
  },
  {
    "type": 2,
    "word": "poloc"
  },
  {
    "type": 2,
    "word": "ponyplay"
  },
  {
    "type": 2,
    "word": "poonan"
  },
  {
    "type": 2,
    "word": "poontang"
  },
  {
    "type": 2,
    "word": "poopchu"
  },
  {
    "type": 2,
    "word": "porchmonk"
  },
  {
    "type": 2,
    "word": "porn"
  },
  {
    "type": 2,
    "word": "pthc"
  },
  {
    "type": 2,
    "word": "puchang"
  },
  {
    "type": 2,
    "word": "pukeng"
  },
  {
    "type": 2,
    "word": "punan"
  },
  {
    "type": 2,
    "word": "punta"
  },
  {
    "type": 2,
    "word": "punyeta"
  },
  {
    "type": 2,
    "word": "pussies"
  },
  {
    "type": 2,
    "word": "pussy"
  },
  {
    "type": 2,
    "word": "putain"
  },
  {
    "type": 2,
    "word": "putangin"
  },
  {
    "type": 2,
    "word": "queaf"
  },
  {
    "type": 2,
    "word": "queef"
  },
  {
    "type": 2,
    "word": "queer"
  },
  {
    "type": 2,
    "word": "raghead"
  },
  {
    "type": 2,
    "word": "ratbu"
  },
  {
    "type": 2,
    "word": "rectum"
  },
  {
    "type": 2,
    "word": "renob"
  },
  {
    "type": 2,
    "word": "rimjob"
  },
  {
    "type": 2,
    "word": "ruski"
  },
  {
    "type": 2,
    "word": "Saan"
  },
  {
    "type": 2,
    "word": "saklolo"
  },
  {
    "type": 2,
    "word": "Salamat"
  },
  {
    "type": 2,
    "word": "salope"
  },
  {
    "type": 2,
    "word": "Sandali"
  },
  {
    "type": 2,
    "word": "sandnig"
  },
  {
    "type": 2,
    "word": "santorum"
  },
  {
    "type": 2,
    "word": "sayaw"
  },
  {
    "type": 2,
    "word": "Scheisse"
  },
  {
    "type": 2,
    "word": "scheisskopf"
  },
  {
    "type": 2,
    "word": "schlong"
  },
  {
    "type": 2,
    "word": "Schwanz"
  },
  {
    "type": 2,
    "word": "seex"
  },
  {
    "type": 2,
    "word": "sex"
  },
  {
    "type": 2,
    "word": "shemal"
  },
  {
    "type": 2,
    "word": "shitas"
  },
  {
    "type": 2,
    "word": "shitb"
  },
  {
    "type": 2,
    "word": "shitc"
  },
  {
    "type": 2,
    "word": "shitd"
  },
  {
    "type": 2,
    "word": "shith"
  },
  {
    "type": 2,
    "word": "shitsp"
  },
  {
    "type": 2,
    "word": "shitst"
  },
  {
    "type": 2,
    "word": "shitter"
  },
  {
    "type": 2,
    "word": "shitting"
  },
  {
    "type": 2,
    "word": "shrimping"
  },
  {
    "type": 2,
    "word": "sipsipin"
  },
  {
    "type": 2,
    "word": "slanteye"
  },
  {
    "type": 2,
    "word": "slut"
  },
  {
    "type": 2,
    "word": "smegma"
  },
  {
    "type": 2,
    "word": "sodom"
  },
  {
    "type": 2,
    "word": "splooge"
  },
  {
    "type": 2,
    "word": "spooge"
  },
  {
    "type": 2,
    "word": "squirting"
  },
  {
    "type": 2,
    "word": "strappado"
  },
  {
    "type": 2,
    "word": "sucka"
  },
  {
    "type": 2,
    "word": "sumayaw"
  },
  {
    "type": 2,
    "word": "suwerte"
  },
  {
    "type": 2,
    "word": "suwertehin"
  },
  {
    "type": 2,
    "word": "swastika"
  },
  {
    "type": 2,
    "word": "tagalog"
  },
  {
    "type": 2,
    "word": "Tahtlo"
  },
  {
    "type": 2,
    "word": "tantouze"
  },
  {
    "type": 2,
    "word": "tarantado"
  },
  {
    "type": 2,
    "word": "Tauyo"
  },
  {
    "type": 2,
    "word": "teen2te"
  },
  {
    "type": 2,
    "word": "teen4te"
  },
  {
    "type": 2,
    "word": "teenforte"
  },
  {
    "type": 2,
    "word": "teenonte"
  },
  {
    "type": 2,
    "word": "teensforte"
  },
  {
    "type": 2,
    "word": "teensonte"
  },
  {
    "type": 2,
    "word": "testicle"
  },
  {
    "type": 2,
    "word": "throating"
  },
  {
    "type": 2,
    "word": "titandass"
  },
  {
    "type": 2,
    "word": "tontopollas"
  },
  {
    "type": 2,
    "word": "towelhead"
  },
  {
    "type": 2,
    "word": "tranny"
  },
  {
    "type": 2,
    "word": "trouducul"
  },
  {
    "type": 2,
    "word": "tubgirl"
  },
  {
    "type": 2,
    "word": "tumawa"
  },
  {
    "type": 2,
    "word": "tushy"
  },
  {
    "type": 2,
    "word": "twatlip"
  },
  {
    "type": 2,
    "word": "twatw"
  },
  {
    "type": 2,
    "word": "twink"
  },
  {
    "type": 2,
    "word": "umaga"
  },
  {
    "type": 2,
    "word": "urethra"
  },
  {
    "type": 2,
    "word": "uroph"
  },
  {
    "type": 2,
    "word": "vagina"
  },
  {
    "type": 2,
    "word": "vagita"
  },
  {
    "type": 2,
    "word": "vajayjay"
  },
  {
    "type": 2,
    "word": "velhaco"
  },
  {
    "type": 2,
    "word": "vjayjay"
  },
  {
    "type": 2,
    "word": "vorareph"
  },
  {
    "type": 2,
    "word": "vulva"
  },
  {
    "type": 2,
    "word": "vvvv"
  },
  {
    "type": 2,
    "word": "Walang"
  },
  {
    "type": 2,
    "word": "wank"
  },
  {
    "type": 2,
    "word": "wetback"
  },
  {
    "type": 2,
    "word": "wh0re"
  },
  {
    "type": 2,
    "word": "whitepow"
  },
  {
    "type": 2,
    "word": "whore"
  },
  {
    "type": 2,
    "word": "whorre"
  },
  {
    "type": 2,
    "word": "Wichser"
  },
  {
    "type": 2,
    "word": "www."
  },
  {
    "type": 2,
    "word": "yiffy"
  },
  {
    "type": 2,
    "word": "youaregay"
  },
  {
    "type": 2,
    "word": "yourgay"
  },
  {
    "type": 2,
    "word": "zipperhead"
  },
  {
    "type": 2,
    "word": "zooph"
  },
  {
    "type": 2,
    "word": "b1tch"
  },
  {
    "type": 2,
    "word": "bltch"
  },
  {
    "type": 2,
    "word": "ganja"
  },
  {
    "type": 2,
    "word": "weed"
  },
  {
    "type": 2,
    "word": "sativa"
  },
  {
    "type": 2,
    "word": "cocain"
  },
  {
    "type": 2,
    "word": "heroin"
  },
  {
    "type": 2,
    "word": "marijuana"
  },
  {
    "type": 2,
    "word": "cannabis"
  },
  {
    "type": 2,
    "word": "hashich"
  },
  {
    "type": 2,
    "word": "hashish"
  },
  {
    "type": 2,
    "word": "sativa"
  },
  {
    "type": 2,
    "word": "indica"
  },
  {
    "type": 2,
    "word": "ruderalis"
  }
]
